{
  "grades": [
    {
      "tier": "tier0_cross",
      "q_idx": 0,
      "score": 0.0,
      "label": "no",
      "evidence_quote": "",
      "rationale": "Cross-category description about snowmobiles, not relevant."
    },
    {
      "tier": "tier0_cross",
      "q_idx": 1,
      "score": 0.0,
      "label": "no",
      "evidence_quote": "",
      "rationale": "Describes snowmobiles, not horses. Contradicts answer key."
    },
    {
      "tier": "tier0_cross",
      "q_idx": 2,
      "score": 0.0,
      "label": "no",
      "evidence_quote": "",
      "rationale": "Cross-category; no fence description provided."
    },
    {
      "tier": "tier1_vatex_short",
      "q_idx": 0,
      "score": 0.0,
      "label": "no",
      "evidence_quote": "",
      "rationale": "No headwear color mentioned in description."
    },
    {
      "tier": "tier1_vatex_short",
      "q_idx": 1,
      "score": 1.0,
      "label": "yes",
      "evidence_quote": "rides on a horse",
      "rationale": "Clearly identifies horse as animal type."
    },
    {
      "tier": "tier1_vatex_short",
      "q_idx": 2,
      "score": 0.0,
      "label": "no",
      "evidence_quote": "",
      "rationale": "No fence description provided."
    },
    {
      "tier": "tier2_vatex_long",
      "q_idx": 0,
      "score": 0.0,
      "label": "no",
      "evidence_quote": "",
      "rationale": "No headwear color mentioned."
    },
    {
      "tier": "tier2_vatex_long",
      "q_idx": 1,
      "score": 1.0,
      "label": "yes",
      "evidence_quote": "riding a horse",
      "rationale": "Clearly identifies horse as animal type."
    },
    {
      "tier": "tier2_vatex_long",
      "q_idx": 2,
      "score": 0.0,
      "label": "no",
      "evidence_quote": "",
      "rationale": "Mentions paddock but no fence color or material details."
    },
    {
      "tier": "tier3_va11y",
      "q_idx": 0,
      "score": 1.0,
      "label": "yes",
      "evidence_quote": "woman in a pink cap",
      "rationale": "Explicitly states pink cap color."
    },
    {
      "tier": "tier3_va11y",
      "q_idx": 1,
      "score": 1.0,
      "label": "yes",
      "evidence_quote": "rides a horse",
      "rationale": "Clearly identifies horse as animal type."
    },
    {
      "tier": "tier3_va11y",
      "q_idx": 2,
      "score": 0.5,
      "label": "partial",
      "evidence_quote": "In a fenced paddock",
      "rationale": "Mentions fenced paddock but lacks color and material specifics."
    }
  ]
}